<?xml version="1.0" encoding="UTF-8"?>
<odoo>
    
    <!-- Menu -->
    <menuitem id="estate_menu_root" name="Real Estate">
        <menuitem id="estate_first_level_menu" name="Advertisement">
            <menuitem id="estate_model_menu_action" action="estate_property_action" name="Property"/>
        </menuitem>
    </menuitem>

    <!-- Records -->
    <record id="estate_property_action" model="ir.actions.act_window">
        <field name="name">Estate Property Action</field>
        <field name="res_model">estate.property</field>
        <field name="view_mode">tree,form</field>
    </record> 
</odoo>